ccflow_s3/__init__.py
ccflow_s3/base.py
ccflow_s3/tests/test_all.py
ccflow_s3-0.1.0.dist-info/METADATA
ccflow_s3-0.1.0.dist-info/WHEEL
ccflow_s3-0.1.0.dist-info/licenses/LICENSE
ccflow_s3-0.1.0.dist-info/RECORD
